specpipe/__init__.py
specpipe-0.3.7.dist-info/licenses/LICENSE
specpipe-0.3.7.dist-info/METADATA
specpipe-0.3.7.dist-info/WHEEL
specpipe-0.3.7.dist-info/top_level.txt
specpipe-0.3.7.dist-info/RECORD
