Metadata-Version: 2.4
Name: specpipe
Version: 0.3.7
Summary: Deprecated: this project has been renamed to swectral.
Author-email: Siwei Luo <siwei1102@outlook.de>
License-Expression: MIT
Keywords: hyperspectral-imaging,spectral-image-processing,hyperspectral-modeling,model-evaluation-automation,spectral-modeling-pipeline
Classifier: Development Status :: 7 - Inactive
Classifier: Intended Audience :: Science/Research
Classifier: Programming Language :: Python :: 3
Classifier: Programming Language :: Python :: 3.9
Classifier: Topic :: Scientific/Engineering :: Bio-Informatics
Classifier: Topic :: Scientific/Engineering :: GIS
Classifier: Topic :: Scientific/Engineering :: Image Processing
Classifier: Topic :: Scientific/Engineering :: Artificial Intelligence
Requires-Python: >=3.9
License-File: LICENSE
Dynamic: license-file
